{
  "carts": [
    {
      "id": "1",
      "productId": 20,
      "cartQuantity": 2,
      "cartTotalPrice": 60000,
      "userId": 1
    },
    {
      "id": "2",
      "productId": 7,
      "cartQuantity": 3,
      "cartTotalPrice": 45000,
      "userId": 1
    },
    {
      "id": "3",
      "productId": 15,
      "cartQuantity": 1,
      "cartTotalPrice": 40000,
      "userId": 1
    },
    {
      "id": "4",
      "productId": 19,
      "cartQuantity": 2,
      "cartTotalPrice": 280000,
      "userId": 1
    },
    {
      "id": "5",
      "productId": 17,
      "cartQuantity": 2,
      "cartTotalPrice": 240000,
      "userId": 1
    },
    {
      "id": "6",
      "productId": 11,
      "cartQuantity": 2,
      "cartTotalPrice": 120000,
      "userId": 1
    },
    {
      "id": "7",
      "productId": 5,
      "cartQuantity": 5,
      "cartTotalPrice": 250000,
      "userId": 2
    },
    {
      "id": "8",
      "productId": 16,
      "cartQuantity": 3,
      "cartTotalPrice": 30000,
      "userId": 2
    },
    {
      "id": "9",
      "productId": 12,
      "cartQuantity": 1,
      "cartTotalPrice": 70000,
      "userId": 2
    },
    {
      "id": "10",
      "productId": 1,
      "cartQuantity": 2,
      "cartTotalPrice": 8000,
      "userId": 2
    },
    {
      "id": "11",
      "productId": 2,
      "cartQuantity": 7,
      "cartTotalPrice": 56000,
      "userId": 2
    },
    {
      "id": "12",
      "productId": 10,
      "cartQuantity": 1,
      "cartTotalPrice": 50000,
      "userId": 3
    },
    {
      "id": "13",
      "productId": 3,
      "cartQuantity": 5,
      "cartTotalPrice": 60000,
      "userId": 3
    },
    {
      "id": "14",
      "productId": 13,
      "cartQuantity": 1,
      "cartTotalPrice": 80000,
      "userId": 3
    },
    {
      "id": "15",
      "productId": 18,
      "cartQuantity": 2,
      "cartTotalPrice": 260000,
      "userId": 3
    },
    {
      "id": "16",
      "productId": 9,
      "cartQuantity": 1,
      "cartTotalPrice": 40000,
      "userId": 3
    }
  ]
}
